{
  "recipes": [
    {
      "id": "1",
      "name": "fish",
      "description": "Tender beef simmered with carrots and potatoes.",
      "ingredients": "Beef, carrots, potatoes, onions, garlic, tomato paste, spices",
      "instructions": "Brown beef, add chopped veggies, simmer until soft and flavorful.",
      "image": "/beef_stew.jpeg"
    },
    {
      "id": "4",
      "name": "Luo-Style Fried Tilapia",
      "description": "Whole tilapia fish deep-fried and served with ugali and sautéed greens.",
      "ingredients": "Whole tilapia, salt, lemon juice, garlic, cooking oil, sukuma wiki, maize flour",
      "instructions": "Clean and score the fish. Marinate with salt, garlic, and lemon. Deep-fry until golden brown. Serve with ugali and fried sukuma wiki.",
      "image": "/fish_fry.jpeg"
    },
    {
      "id": "2",
      "name": "Mango juice",
      "description": "Refreshing tropical drink for hot days.",
      "ingredients": "Ripe mangoes, yogurt, honey, ice cubes",
      "instructions": "Blend all ingredients until smooth. Serve chilled.",
      "image": "/mango_milkshake.jpeg"
    },
    {
      "id": "3",
      "name": "Vegetable Stir-Fry",
      "description": "Colorful, crunchy veggies stir-fried in soy sauce.",
      "ingredients": "Bell peppers, broccoli, carrots, soy sauce, garlic, sesame oil",
      "instructions": "Stir-fry veggies on high heat for 5–7 mins with sauce.",
      "image": "/summer_veggies.jpeg"
    },
    {
      "id": "5",
      "name": "Classic Pancakes",
      "description": "Fluffy breakfast pancakes perfect with syrup or fruit.",
      "ingredients": "Flour, milk, eggs, sugar, baking powder, butter, salt",
      "instructions": "Mix ingredients into a batter, cook on a hot pan until golden brown.",
      "image": "/fluffy_pancake.jpeg"
    }
  ]
}
